Metadata-Version: 2.2
Name: mantacoder
Version: 0.2.0.1
Summary: A Python library for Code Agent MantaCoder
Author: Heng Ji
Author-email: jihengcu@gmail.com
Project-URL: Homepage, https://github.com/hengjiUSTC/mantacoder
Project-URL: Bug Tracker, https://github.com/hengjiUSTC/mantacoder/issues
Project-URL: Documentation, https://github.com/hengjiUSTC/mantacoder#readme
Project-URL: Source Code, https://github.com/hengjiUSTC/mantacoder
Classifier: Programming Language :: Python :: 3
Classifier: Programming Language :: Python :: 3.6
Classifier: Programming Language :: Python :: 3.7
Classifier: Programming Language :: Python :: 3.8
Classifier: Programming Language :: Python :: 3.9
Classifier: License :: OSI Approved :: MIT License
Classifier: Operating System :: OS Independent
Requires-Python: >=3.6
License-File: LICENSE
Requires-Dist: requests>=2.26.0
Requires-Dist: dataclasses>=0.8; python_version < "3.7"
Requires-Dist: prompt_toolkit>=3.0.0
Requires-Dist: typing-extensions>=4.0.0
Requires-Dist: openai>=1.60.0
Requires-Dist: pytest>=8.0.0
Requires-Dist: unidiff>=0.7.0
Requires-Dist: tiktoken>=0.8.0
Requires-Dist: rich>=13.0.0
Provides-Extra: dev
Requires-Dist: black; extra == "dev"
Requires-Dist: isort; extra == "dev"
Requires-Dist: flake8; extra == "dev"
Requires-Dist: mypy; extra == "dev"
Requires-Dist: pytest; extra == "dev"
Requires-Dist: pre_commit; extra == "dev"
Dynamic: author
Dynamic: author-email
Dynamic: classifier
Dynamic: description
Dynamic: description-content-type
Dynamic: project-url
Dynamic: provides-extra
Dynamic: requires-dist
Dynamic: requires-python
Dynamic: summary
